LICENSE
LICENSE-THIRD-PARTY
yls/__init__.py
yls/code_actions.py
yls/completer.py
yls/completion.py
yls/debugger.py
yls/hookspecs.py
yls/hover.py
yls/icons.py
yls/linting.py
yls/plugin_manager_provider.py
yls/py.typed
yls/server.py
yls/strings.py
yls/utils.py
yls/version.py
yls/yaramod_provider.py
yls_macos_arm-1.4.2.dist-info/LICENSE
yls_macos_arm-1.4.2.dist-info/METADATA
yls_macos_arm-1.4.2.dist-info/WHEEL
yls_macos_arm-1.4.2.dist-info/entry_points.txt
yls_macos_arm-1.4.2.dist-info/RECORD
