Metadata-Version: 2.1
Name: yls-macos-arm
Version: 1.4.2
Summary: YARA Language Server
License: MIT
Author: Matej Kašťák
Author-email: matej.kastak@avast.com
Maintainer: Nils Kuhnert
Maintainer-email: 3c7@posteo.de
Requires-Python: >=3.11,<3.13
Classifier: License :: OSI Approved :: MIT License
Classifier: Programming Language :: Python :: 3
Classifier: Programming Language :: Python :: 3.11
Classifier: Programming Language :: Python :: 3.12
Requires-Dist: pluggy (>=1.0.0,<2.0.0)
Requires-Dist: pygls (>=1.3.0,<2.0.0)
Requires-Dist: yaramod (>=3.21.0,<4.0.0)
Requires-Dist: yari-py-macos-arm (>=0.2.1,<0.3.0)
